scmomat/__init__.py
scmomat/__version__.py
scmomat/bmk.py
scmomat/model.py
scmomat/umap_batch.py
scmomat/utils.py
scmomat-0.2.2.dist-info/LICENSE
scmomat-0.2.2.dist-info/METADATA
scmomat-0.2.2.dist-info/WHEEL
scmomat-0.2.2.dist-info/top_level.txt
scmomat-0.2.2.dist-info/RECORD
