Metadata-Version: 2.1
Name: scmomat
Version: 0.2.2
Summary: scmomat: a single-cell multi-omics mosaic integration method
Home-page: https://github.com/PeterZZQ/scMoMaT
Author: Ziqi Zhang
Author-email: zhangziqibuaa@gmail.com
License: MIT
Classifier: License :: OSI Approved :: MIT License
Classifier: Programming Language :: Python
Classifier: Programming Language :: Python :: 3
Classifier: Programming Language :: Python :: 3.8
Classifier: Programming Language :: Python :: Implementation :: CPython
Classifier: Programming Language :: Python :: Implementation :: PyPy
Classifier: Topic :: Scientific/Engineering :: Bio-Informatics
Classifier: Operating System :: POSIX :: Linux
Classifier: Operating System :: MacOS :: MacOS X
Requires-Python: >=3.8.10
License-File: LICENSE
Requires-Dist: torch (>=1.11.0)
Requires-Dist: numpy (>=1.19.5)
Requires-Dist: pandas (>=1.4.0)
Requires-Dist: scipy (>=1.7.3)
Requires-Dist: scikit-learn (>=0.22.1)
Requires-Dist: umap-learn (>=0.5.2)
Requires-Dist: matplotlib (>=3.5.2)
Requires-Dist: leidenalg (>=0.9.1)
